{"image_id": 586, "abs_t": "6,p_4s.png,0,4,1,256,258,1,1,hb0_12s.png,1,12,2,410,209,2,1,hb1_11s.png,2,11,3,64,341,2,0,e_6s.png,3,6,6,467,340,0,0,e_1s.png,4,1,6,403,349,0,1,t_4s.png,5,4,7,140,347,1,1", "socketId": "/#z1hdMjPFS42JJ6NqAG4H/#7fiV5Z19CFqAs2vJAG4G", "dialog": [{"seq_t": "1", "abs_b": "", "msg_d": "hi", "abs_d": "", "seq_d": "1", "score": [], "msg_t": "hi"}, {"seq_t": "2", "abs_b": "", "msg_d": "ok", "abs_d": "", "seq_d": "2", "score": [], "msg_t": "in the center is a swing set . there is a small girl left of the swing kicking a soccer ball ."}, {"seq_t": "3", "abs_b": "", "msg_d": "ok", "abs_d": "", "seq_d": "3", "score": [], "msg_t": "on the right side on the ground is a pizza and a drink"}, {"seq_t": "4", "abs_b": "", "msg_d": "ok", "abs_d": "", "seq_d": "4", "score": [], "msg_t": "in the background is a happy boy kicking"}, {"seq_t": "5", "abs_b": "", "msg_d": "thank you", "abs_d": "28,s_7s.png,0,7,0,-10000,-10000,0,1,s_0s.png,1,0,0,-10000,-10000,0,0,s_1s.png,2,1,0,-10000,-10000,0,1,p_4s.png,3,4,1,246,248,1,1,p_0s.png,4,0,1,-10000,-10000,0,1,p_1s.png,5,1,1,-10000,-10000,0,0,p_3s.png,6,3,1,-10000,-10000,0,0,hb0_12s.png,7,12,2,443,201,2,1,hb0_19s.png,8,19,2,-10000,-10000,0,0,hb0_1s.png,9,1,2,-10000,-10000,0,0,hb0_9s.png,10,9,2,-10000,-10000,0,0,hb0_31s.png,11,31,2,-10000,-10000,0,0,hb1_2s.png,12,2,3,-10000,-10000,0,0,hb1_20s.png,13,20,3,-10000,-10000,0,0,hb1_19s.png,14,19,3,-10000,-10000,0,0,hb1_11s.png,15,11,3,56,341,2,0,hb1_16s.png,16,16,3,-10000,-10000,0,0,a_0s.png,17,0,4,-10000,-10000,0,0,a_1s.png,18,1,4,-10000,-10000,0,0,c_4s.png,19,4,5,-10000,-10000,0,1,c_0s.png,20,0,5,-10000,-10000,0,1,c_7s.png,21,7,5,-10000,-10000,0,0,e_6s.png,22,6,6,470,367,0,0,e_1s.png,23,1,6,383,373,0,1,t_6s.png,24,6,7,-10000,-10000,0,1,t_4s.png,25,4,7,145,353,1,1,t_1s.png,26,1,7,-10000,-10000,0,0,t_8s.png,27,8,7,-10000,-10000,0,0,", "seq_d": "5", "score": [4.898630393834363, [5, -1, -1, -1, -1, -0.5, -0.5], [1, 0, 0, 0, 0.045814050610081626, 0, 0.1111111111111111], [5, 0, 0, 0, -0.045814050610081626, 0, -0.05555555555555555]], "msg_t": "that is everything ."}]}