{"image_id": 9997, "abs_t": "6,s_3s.png,0,3,0,455,37,1,0,s_2s.png,1,2,0,374,60,2,0,p_0s.png,2,0,1,240,331,0,1,hb0_9s.png,3,9,2,97,241,0,0,hb1_3s.png,4,3,3,429,251,0,1,t_6s.png,5,6,7,100,122,0,0", "socketId": "/#I2XRaX41H0-5tvqTAErw/#I2fHGJsD7AdR_Mx2AErv", "dialog": [{"seq_t": "1", "abs_b": "", "msg_d": "hi", "abs_d": "", "seq_d": "1", "score": [], "msg_t": "hi"}, {"seq_t": "2", "abs_b": "", "msg_d": "ok", "abs_d": "", "seq_d": "2", "score": [], "msg_t": "there is a sun in the upper right with a small cloud the the left of it"}, {"seq_t": "3", "abs_b": "", "msg_d": "ok", "abs_d": "", "seq_d": "3", "score": [], "msg_t": "to the left is a surprised boy holding a football above his head ."}, {"seq_t": "4", "abs_b": "", "msg_d": "ok", "abs_d": "", "seq_d": "4", "score": [], "msg_t": "at the bottom center is a spring be and to the very right is a sad girl holding out her hands"}, {"seq_t": "5", "abs_b": "", "msg_d": "alright , thank you", "abs_d": "28,s_3s.png,0,3,0,460,51,1,0,s_2s.png,1,2,0,371,63,2,1,s_1s.png,2,1,0,-10000,-10000,0,1,p_7s.png,3,7,1,-10000,-10000,0,1,p_2s.png,4,2,1,-10000,-10000,0,1,p_0s.png,5,0,1,258,311,0,1,p_1s.png,6,1,1,-10000,-10000,0,0,hb0_29s.png,7,29,2,-10000,-10000,0,0,hb0_9s.png,8,9,2,74,264,0,0,hb0_11s.png,9,11,2,-10000,-10000,0,0,hb0_0s.png,10,0,2,-10000,-10000,0,0,hb0_28s.png,11,28,2,-10000,-10000,0,1,hb1_30s.png,12,30,3,-10000,-10000,0,0,hb1_24s.png,13,24,3,-10000,-10000,0,0,hb1_7s.png,14,7,3,-10000,-10000,0,0,hb1_3s.png,15,3,3,-10000,-10000,0,0,hb1_2s.png,16,2,3,424,255,0,1,a_4s.png,17,4,4,-10000,-10000,0,0,a_5s.png,18,5,4,-10000,-10000,0,1,c_4s.png,19,4,5,-10000,-10000,0,1,c_8s.png,20,8,5,-10000,-10000,0,1,c_7s.png,21,7,5,-10000,-10000,0,0,e_1s.png,22,1,6,-10000,-10000,0,1,e_6s.png,23,6,6,-10000,-10000,0,1,t_6s.png,24,6,7,70,134,0,0,t_13s.png,25,13,7,-10000,-10000,0,1,t_9s.png,26,9,7,-10000,-10000,0,1,t_4s.png,27,4,7,-10000,-10000,0,1,", "seq_d": "5", "score": [4.1506982733303195, [5, -1, -1, -1, -1, -0.5, -0.5], [1, 0.25, 0.5, 0, 0.043746171114125286, 0.05555555555555555, 0.05555555555555555], [5, -0.25, -0.5, 0, -0.043746171114125286, -0.027777777777777776, -0.027777777777777776]], "msg_t": "that is everything . thank you"}]}